[
    {
        "productTitle": "Sky Blue Cotton Fitted Shirt",
        "image": "https://www.aarong.com/media/catalog/product/0/0/0070000054795.jpg?optimize=high&bg-color=255,255,255&fit=bounds&height=400&width=300&canvas=300:400",
        "mainPrice": "4069.77",
        "price": "3290.55",
        "category": "Man",
        "subCategory": "shirt",
        "size": "M",
        "quantity": 0,
        "bestDeal": true,
        "weight": 45,
        "des": "Sky blue cotton fitted shirt. Features chest pocket and standard placket."
      },
    {
        "productTitle": "Sky Blue Cotton Fitted Shirt",
        "image": "https://www.aarong.com/media/catalog/product/0/0/0070000054795.jpg?optimize=high&bg-color=255,255,255&fit=bounds&height=400&width=300&canvas=300:400",
        "mainPrice": "4069.77",
        "price": "3290.55",
        "category": "Man",
        "subCategory": "shirt",
        "size": "M",
        "quantity": 0,
        "bestDeal": true,
        "weight": 45,
        "des": "Sky blue cotton fitted shirt. Features chest pocket and standard placket."
      }
]